django_log_lens/__init__.py
django_log_lens/apps.py
django_log_lens/urls.py
django_log_lens/views.py
django_log_lens/static/django_log_lens/favicon.svg
django_log_lens/static/django_log_lens/logger.js
django_log_lens/static/django_log_lens/logo.svg
django_log_lens/static/django_log_lens/script.js
django_log_lens/static/django_log_lens/styles.css
django_log_lens/templates/js-logger.html
django_log_lens/templates/log-lens-login.html
django_log_lens/templates/log-lens.html
django_log_lens-1.0.0.dist-info/licenses/LICENSE.txt
django_log_lens-1.0.0.dist-info/METADATA
django_log_lens-1.0.0.dist-info/WHEEL
django_log_lens-1.0.0.dist-info/top_level.txt
django_log_lens-1.0.0.dist-info/RECORD
