Metadata-Version: 2.4
Name: django-log-lens
Version: 1.0.0
Summary: A lightweight Django app for viewing and managing log data conveniently
Home-page: https://github.com/martinbroede/django-log-lens
Author: Martin Broede
Author-email: martin.broede@gmail.com
Maintainer: Martin Broede
Maintainer-email: martin.broede@gmail.com
License: MIT
Classifier: Programming Language :: Python :: 3
Classifier: License :: OSI Approved :: MIT License
Classifier: Operating System :: OS Independent
Classifier: Framework :: Django
Classifier: Development Status :: 5 - Production/Stable
Classifier: Intended Audience :: Developers
Classifier: Topic :: Software Development :: Libraries :: Python Modules
Classifier: Natural Language :: English
Requires-Python: >=3.10
License-File: LICENSE.txt
Requires-Dist: Django>=4.1
Dynamic: author
Dynamic: author-email
Dynamic: classifier
Dynamic: description
Dynamic: description-content-type
Dynamic: home-page
Dynamic: license
Dynamic: license-file
Dynamic: maintainer
Dynamic: maintainer-email
Dynamic: requires-dist
Dynamic: requires-python
Dynamic: summary
